Metadata-Version: 2.1
Name: fourier-grx-dds
Version: 0.2.8.dev1
Classifier: Programming Language :: Python :: 3
Requires-Python: >=3.10
Requires-Dist: numpy>=1.24.0
Requires-Dist: omegaconf>=2.3.0
Requires-Dist: pin-pink>=3.0.0
Requires-Dist: meshcat>=0.3.2
Requires-Dist: loguru>=0.7.2
